{"date":"2022-12-01","day":"목","time":"19:30","스위니토드":"강필석","러빗부인":"전미도","터핀판사":"김대종","안소니":"진태화","토비아스":"윤은오","조안나":"최서연"}
{"date":"2022-12-02","day":"금","time":"19:30","스위니토드":"신성록","러빗부인":"김지현","터핀판사":"박인배","안소니":"노윤","토비아스":"윤석호","조안나":"류인아"}
{"date":"2022-12-03","day":"토","time":"14:00","스위니토드":"이규형","러빗부인":"린아","터핀판사":"김대종","안소니":"진태화","토비아스":"윤은오","조안나":"최서연"}
{"date":"2022-12-03","day":"토","time":"19:00","스위니토드":"강필석","러빗부인":"김지현","터핀판사":"김대종","안소니":"진태화","토비아스":"윤석오","조안나":"류인아"}
{"date":"2022-12-04","day":"일","time":"14:00","스위니토드":"신성록","러빗부인":"린아","터핀판사":"박인배","안소니":"노윤","토비아스":"윤은오","조안나":"최서연"}
{"date":"2022-12-04","day":"일","time":"19:00","스위니토드":"이규형","러빗부인":"전미도","터핀판사":"박인배","안소니":"노윤","토비아스":"윤석오","조안나":"류인아"}
{"date":"2022-12-06","day":"화","time":"19:30","스위니토드":"이규형","러빗부인":"린아","터핀판사":"김대종","안소니":"노윤","토비아스":"윤석오","조안나":"최서연"}
{"date":"2022-12-07","day":"수","time":"19:30","스위니토드":"신성록","러빗부인":"전미도","터핀판사":"박인배","안소니":"진태화","토비아스":"윤은오","조안나":"류인아"}
{"date":"2022-12-08","day":"목","time":"19:30","스위니토드":"강필석","러빗부인":"전미도","터핀판사":"김대종","안소니":"진태화","토비아스":"윤은오","조안나":"최서연"}
{"date":"2022-12-09","day":"금","time":"19:30","스위니토드":"신성록","러빗부인":"김지현","터핀판사":"박인배","안소니":"노윤","토비아스":"윤석호","조안나":"류인아"}
{"date":"2022-12-10","day":"토","time":"14:00","스위니토드":"이규형","러빗부인":"린아","터핀판사":"김대종","안소니":"진태화","토비아스":"윤은오","조안나":"최서연"}
{"date":"2022-12-10","day":"토","time":"19:00","스위니토드":"강필석","러빗부인":"김지현","터핀판사":"김대종","안소니":"진태화","토비아스":"윤석오","조안나":"류인아"}
{"date":"2022-12-11","day":"일","time":"14:00","스위니토드":"신성록","러빗부인":"린아","터핀판사":"박인배","안소니":"노윤","토비아스":"윤은오","조안나":"최서연"}
{"date":"2022-12-11","day":"일","time":"19:00","스위니토드":"이규형","러빗부인":"전미도","터핀판사":"박인배","안소니":"노윤","토비아스":"윤석오","조안나":"류인아"}
{"date":"2022-12-13","day":"화","time":"19:30","스위니토드":"이규형","러빗부인":"린아","터핀판사":"김대종","안소니":"노윤","토비아스":"윤석오","조안나":"최서연"}
{"date":"2022-12-14","day":"수","time":"19:30","스위니토드":"신성록","러빗부인":"전미도","터핀판사":"박인배","안소니":"진태화","토비아스":"윤은오","조안나":"류인아"}
{"date":"2022-12-15","day":"목","time":"19:30","스위니토드":"강필석","러빗부인":"전미도","터핀판사":"김대종","안소니":"진태화","토비아스":"윤은오","조안나":"최서연"}
{"date":"2022-12-16","day":"금","time":"19:30","스위니토드":"신성록","러빗부인":"김지현","터핀판사":"박인배","안소니":"노윤","토비아스":"윤석호","조안나":"류인아"}
{"date":"2022-12-17","day":"토","time":"14:00","스위니토드":"이규형","러빗부인":"린아","터핀판사":"김대종","안소니":"진태화","토비아스":"윤은오","조안나":"최서연"}
{"date":"2022-12-17","day":"토","time":"19:00","스위니토드":"강필석","러빗부인":"김지현","터핀판사":"김대종","안소니":"진태화","토비아스":"윤석오","조안나":"류인아"}
{"date":"2022-12-18","day":"일","time":"14:00","스위니토드":"신성록","러빗부인":"린아","터핀판사":"박인배","안소니":"노윤","토비아스":"윤은오","조안나":"최서연"}
{"date":"2022-12-18","day":"일","time":"19:00","스위니토드":"이규형","러빗부인":"전미도","터핀판사":"박인배","안소니":"노윤","토비아스":"윤석오","조안나":"류인아"}
{"date":"2022-12-20","day":"화","time":"19:30","스위니토드":"이규형","러빗부인":"린아","터핀판사":"김대종","안소니":"노윤","토비아스":"윤석오","조안나":"최서연"}
{"date":"2022-12-21","day":"수","time":"19:30","스위니토드":"신성록","러빗부인":"전미도","터핀판사":"박인배","안소니":"진태화","토비아스":"윤은오","조안나":"류인아"}
{"date":"2022-12-22","day":"목","time":"19:30","스위니토드":"강필석","러빗부인":"전미도","터핀판사":"김대종","안소니":"진태화","토비아스":"윤은오","조안나":"최서연"}
{"date":"2022-12-23","day":"금","time":"19:30","스위니토드":"신성록","러빗부인":"김지현","터핀판사":"박인배","안소니":"노윤","토비아스":"윤석호","조안나":"류인아"}
{"date":"2022-12-24","day":"토","time":"14:00","스위니토드":"이규형","러빗부인":"린아","터핀판사":"김대종","안소니":"진태화","토비아스":"윤은오","조안나":"최서연"}
{"date":"2022-12-24","day":"토","time":"19:00","스위니토드":"강필석","러빗부인":"김지현","터핀판사":"김대종","안소니":"진태화","토비아스":"윤석오","조안나":"류인아"}
{"date":"2022-12-25","day":"일","time":"14:00","스위니토드":"신성록","러빗부인":"린아","터핀판사":"박인배","안소니":"노윤","토비아스":"윤은오","조안나":"최서연"}
{"date":"2022-12-25","day":"일","time":"19:00","스위니토드":"이규형","러빗부인":"전미도","터핀판사":"박인배","안소니":"노윤","토비아스":"윤석오","조안나":"류인아"}
{"date":"2022-12-27","day":"화","time":"19:30","스위니토드":"이규형","러빗부인":"린아","터핀판사":"김대종","안소니":"노윤","토비아스":"윤석오","조안나":"최서연"}
{"date":"2022-12-28","day":"수","time":"19:30","스위니토드":"신성록","러빗부인":"전미도","터핀판사":"박인배","안소니":"진태화","토비아스":"윤은오","조안나":"류인아"}
{"date":"2022-12-29","day":"목","time":"19:30","스위니토드":"강필석","러빗부인":"전미도","터핀판사":"김대종","안소니":"진태화","토비아스":"윤은오","조안나":"최서연"}
{"date":"2022-12-30","day":"금","time":"19:30","스위니토드":"신성록","러빗부인":"김지현","터핀판사":"박인배","안소니":"노윤","토비아스":"윤석호","조안나":"류인아"}
{"date":"2022-12-31","day":"토","time":"14:00","스위니토드":"이규형","러빗부인":"린아","터핀판사":"김대종","안소니":"진태화","토비아스":"윤은오","조안나":"최서연"}
{"date":"2022-12-31","day":"토","time":"19:00","스위니토드":"강필석","러빗부인":"김지현","터핀판사":"김대종","안소니":"진태화","토비아스":"윤석오","조안나":"류인아"}
{"date":"2023-01-01","day":"일","time":"14:00","스위니토드":"신성록","러빗부인":"린아","터핀판사":"박인배","안소니":"노윤","토비아스":"윤은오","조안나":"최서연"}
{"date":"2023-01-01","day":"일","time":"19:00","스위니토드":"이규형","러빗부인":"전미도","터핀판사":"박인배","안소니":"노윤","토비아스":"윤석오","조안나":"류인아"}
{"date":"2023-01-03","day":"화","time":"19:30","스위니토드":"이규형","러빗부인":"린아","터핀판사":"김대종","안소니":"노윤","토비아스":"윤석오","조안나":"최서연"}
{"date":"2023-01-04","day":"수","time":"19:30","스위니토드":"신성록","러빗부인":"전미도","터핀판사":"박인배","안소니":"진태화","토비아스":"윤은오","조안나":"류인아"}
{"date":"2023-01-05","day":"목","time":"19:30","스위니토드":"강필석","러빗부인":"전미도","터핀판사":"김대종","안소니":"진태화","토비아스":"윤은오","조안나":"최서연"}
{"date":"2023-01-06","day":"금","time":"19:30","스위니토드":"신성록","러빗부인":"김지현","터핀판사":"박인배","안소니":"노윤","토비아스":"윤석호","조안나":"류인아"}
{"date":"2023-01-07","day":"토","time":"14:00","스위니토드":"이규형","러빗부인":"린아","터핀판사":"김대종","안소니":"진태화","토비아스":"윤은오","조안나":"최서연"}
{"date":"2023-01-07","day":"토","time":"19:00","스위니토드":"강필석","러빗부인":"김지현","터핀판사":"김대종","안소니":"진태화","토비아스":"윤석오","조안나":"류인아"}
{"date":"2023-01-08","day":"일","time":"14:00","스위니토드":"신성록","러빗부인":"린아","터핀판사":"박인배","안소니":"노윤","토비아스":"윤은오","조안나":"최서연"}
{"date":"2023-01-08","day":"일","time":"19:00","스위니토드":"이규형","러빗부인":"전미도","터핀판사":"박인배","안소니":"노윤","토비아스":"윤석오","조안나":"류인아"}
{"date":"2023-01-09","day":"화","time":"19:30","스위니토드":"이규형","러빗부인":"린아","터핀판사":"김대종","안소니":"노윤","토비아스":"윤석오","조안나":"최서연"}
{"date":"2023-01-10","day":"수","time":"19:30","스위니토드":"신성록","러빗부인":"전미도","터핀판사":"박인배","안소니":"진태화","토비아스":"윤은오","조안나":"류인아"}
{"date":"2023-01-11","day":"목","time":"19:30","스위니토드":"강필석","러빗부인":"전미도","터핀판사":"김대종","안소니":"진태화","토비아스":"윤은오","조안나":"최서연"}
{"date":"2023-01-12","day":"금","time":"19:30","스위니토드":"신성록","러빗부인":"김지현","터핀판사":"박인배","안소니":"노윤","토비아스":"윤석호","조안나":"류인아"}
{"date":"2023-01-13","day":"토","time":"14:00","스위니토드":"이규형","러빗부인":"린아","터핀판사":"김대종","안소니":"진태화","토비아스":"윤은오","조안나":"최서연"}
{"date":"2023-01-13","day":"토","time":"19:00","스위니토드":"강필석","러빗부인":"김지현","터핀판사":"김대종","안소니":"진태화","토비아스":"윤석오","조안나":"류인아"}
{"date":"2023-01-14","day":"일","time":"14:00","스위니토드":"신성록","러빗부인":"린아","터핀판사":"박인배","안소니":"노윤","토비아스":"윤은오","조안나":"최서연"}
{"date":"2023-01-14","day":"일","time":"19:00","스위니토드":"이규형","러빗부인":"전미도","터핀판사":"박인배","안소니":"노윤","토비아스":"윤석오","조안나":"류인아"}
{"date":"2023-01-16","day":"화","time":"19:30","스위니토드":"이규형","러빗부인":"린아","터핀판사":"김대종","안소니":"노윤","토비아스":"윤석오","조안나":"최서연"}
{"date":"2023-01-17","day":"수","time":"19:30","스위니토드":"신성록","러빗부인":"전미도","터핀판사":"박인배","안소니":"진태화","토비아스":"윤은오","조안나":"류인아"}
{"date":"2023-01-18","day":"목","time":"19:30","스위니토드":"강필석","러빗부인":"전미도","터핀판사":"김대종","안소니":"진태화","토비아스":"윤은오","조안나":"최서연"}
{"date":"2023-01-19","day":"금","time":"19:30","스위니토드":"신성록","러빗부인":"김지현","터핀판사":"박인배","안소니":"노윤","토비아스":"윤석호","조안나":"류인아"}
{"date":"2023-01-20","day":"토","time":"14:00","스위니토드":"이규형","러빗부인":"린아","터핀판사":"김대종","안소니":"진태화","토비아스":"윤은오","조안나":"최서연"}
{"date":"2023-01-20","day":"토","time":"19:00","스위니토드":"강필석","러빗부인":"김지현","터핀판사":"김대종","안소니":"진태화","토비아스":"윤석오","조안나":"류인아"}
{"date":"2023-01-21","day":"일","time":"14:00","스위니토드":"신성록","러빗부인":"린아","터핀판사":"박인배","안소니":"노윤","토비아스":"윤은오","조안나":"최서연"}
{"date":"2023-01-21","day":"일","time":"19:00","스위니토드":"이규형","러빗부인":"전미도","터핀판사":"박인배","안소니":"노윤","토비아스":"윤석오","조안나":"류인아"}
{"date":"2023-01-23","day":"화","time":"19:30","스위니토드":"이규형","러빗부인":"린아","터핀판사":"김대종","안소니":"노윤","토비아스":"윤석오","조안나":"최서연"}
{"date":"2023-01-24","day":"수","time":"19:30","스위니토드":"신성록","러빗부인":"전미도","터핀판사":"박인배","안소니":"진태화","토비아스":"윤은오","조안나":"류인아"}
{"date":"2023-01-25","day":"목","time":"19:30","스위니토드":"강필석","러빗부인":"전미도","터핀판사":"김대종","안소니":"진태화","토비아스":"윤은오","조안나":"최서연"}
{"date":"2023-01-26","day":"금","time":"19:30","스위니토드":"신성록","러빗부인":"김지현","터핀판사":"박인배","안소니":"노윤","토비아스":"윤석호","조안나":"류인아"}
{"date":"2023-01-27","day":"토","time":"14:00","스위니토드":"이규형","러빗부인":"린아","터핀판사":"김대종","안소니":"진태화","토비아스":"윤은오","조안나":"최서연"}
{"date":"2023-01-27","day":"토","time":"19:00","스위니토드":"강필석","러빗부인":"김지현","터핀판사":"김대종","안소니":"진태화","토비아스":"윤석오","조안나":"류인아"}
{"date":"2023-01-28","day":"일","time":"14:00","스위니토드":"신성록","러빗부인":"린아","터핀판사":"박인배","안소니":"노윤","토비아스":"윤은오","조안나":"최서연"}
{"date":"2023-01-28","day":"일","time":"19:00","스위니토드":"이규형","러빗부인":"전미도","터핀판사":"박인배","안소니":"노윤","토비아스":"윤석오","조안나":"류인아"}
{"date":"2023-01-30","day":"화","time":"19:30","스위니토드":"이규형","러빗부인":"린아","터핀판사":"김대종","안소니":"노윤","토비아스":"윤석오","조안나":"최서연"}
{"date":"2023-01-31","day":"수","time":"19:30","스위니토드":"신성록","러빗부인":"전미도","터핀판사":"박인배","안소니":"진태화","토비아스":"윤은오","조안나":"류인아"}
{"date":"2023-02-01","day":"목","time":"19:30","스위니토드":"강필석","러빗부인":"전미도","터핀판사":"김대종","안소니":"진태화","토비아스":"윤은오","조안나":"최서연"}
{"date":"2023-02-02","day":"금","time":"19:30","스위니토드":"신성록","러빗부인":"김지현","터핀판사":"박인배","안소니":"노윤","토비아스":"윤석호","조안나":"류인아"}
{"date":"2023-02-03","day":"토","time":"14:00","스위니토드":"이규형","러빗부인":"린아","터핀판사":"김대종","안소니":"진태화","토비아스":"윤은오","조안나":"최서연"}
{"date":"2023-02-03","day":"토","time":"19:00","스위니토드":"강필석","러빗부인":"김지현","터핀판사":"김대종","안소니":"진태화","토비아스":"윤석오","조안나":"류인아"}
{"date":"2023-02-04","day":"일","time":"14:00","스위니토드":"신성록","러빗부인":"린아","터핀판사":"박인배","안소니":"노윤","토비아스":"윤은오","조안나":"최서연"}
{"date":"2023-02-04","day":"일","time":"19:00","스위니토드":"이규형","러빗부인":"전미도","터핀판사":"박인배","안소니":"노윤","토비아스":"윤석오","조안나":"류인아"}
{"date":"2023-02-05","day":"화","time":"19:30","스위니토드":"이규형","러빗부인":"린아","터핀판사":"김대종","안소니":"노윤","토비아스":"윤석오","조안나":"최서연"}
{"date":"2023-02-06","day":"수","time":"19:30","스위니토드":"신성록","러빗부인":"전미도","터핀판사":"박인배","안소니":"진태화","토비아스":"윤은오","조안나":"류인아"}
{"date":"2023-02-07","day":"목","time":"19:30","스위니토드":"강필석","러빗부인":"전미도","터핀판사":"김대종","안소니":"진태화","토비아스":"윤은오","조안나":"최서연"}
{"date":"2023-02-08","day":"금","time":"19:30","스위니토드":"신성록","러빗부인":"김지현","터핀판사":"박인배","안소니":"노윤","토비아스":"윤석호","조안나":"류인아"}
{"date":"2023-02-09","day":"토","time":"14:00","스위니토드":"이규형","러빗부인":"린아","터핀판사":"김대종","안소니":"진태화","토비아스":"윤은오","조안나":"최서연"}
{"date":"2023-02-09","day":"토","time":"19:00","스위니토드":"강필석","러빗부인":"김지현","터핀판사":"김대종","안소니":"진태화","토비아스":"윤석오","조안나":"류인아"}
{"date":"2023-02-10","day":"일","time":"14:00","스위니토드":"신성록","러빗부인":"린아","터핀판사":"박인배","안소니":"노윤","토비아스":"윤은오","조안나":"최서연"}
{"date":"2023-02-10","day":"일","time":"19:00","스위니토드":"이규형","러빗부인":"전미도","터핀판사":"박인배","안소니":"노윤","토비아스":"윤석오","조안나":"류인아"}
{"date":"2023-02-11","day":"화","time":"19:30","스위니토드":"이규형","러빗부인":"린아","터핀판사":"김대종","안소니":"노윤","토비아스":"윤석오","조안나":"최서연"}
{"date":"2023-02-12","day":"수","time":"19:30","스위니토드":"신성록","러빗부인":"전미도","터핀판사":"박인배","안소니":"진태화","토비아스":"윤은오","조안나":"류인아"}
{"date":"2023-02-13","day":"목","time":"19:30","스위니토드":"강필석","러빗부인":"전미도","터핀판사":"김대종","안소니":"진태화","토비아스":"윤은오","조안나":"최서연"}
{"date":"2023-02-14","day":"금","time":"19:30","스위니토드":"신성록","러빗부인":"김지현","터핀판사":"박인배","안소니":"노윤","토비아스":"윤석호","조안나":"류인아"}
{"date":"2023-02-15","day":"토","time":"14:00","스위니토드":"이규형","러빗부인":"린아","터핀판사":"김대종","안소니":"진태화","토비아스":"윤은오","조안나":"최서연"}
{"date":"2023-02-15","day":"토","time":"19:00","스위니토드":"강필석","러빗부인":"김지현","터핀판사":"김대종","안소니":"진태화","토비아스":"윤석오","조안나":"류인아"}
{"date":"2023-02-16","day":"일","time":"14:00","스위니토드":"신성록","러빗부인":"린아","터핀판사":"박인배","안소니":"노윤","토비아스":"윤은오","조안나":"최서연"}
{"date":"2023-02-16","day":"일","time":"19:00","스위니토드":"이규형","러빗부인":"전미도","터핀판사":"박인배","안소니":"노윤","토비아스":"윤석오","조안나":"류인아"}
{"date":"2023-02-17","day":"화","time":"19:30","스위니토드":"이규형","러빗부인":"린아","터핀판사":"김대종","안소니":"노윤","토비아스":"윤석오","조안나":"최서연"}
{"date":"2023-02-18","day":"수","time":"19:30","스위니토드":"신성록","러빗부인":"전미도","터핀판사":"박인배","안소니":"진태화","토비아스":"윤은오","조안나":"류인아"}
{"date":"2023-02-19","day":"목","time":"19:30","스위니토드":"강필석","러빗부인":"전미도","터핀판사":"김대종","안소니":"진태화","토비아스":"윤은오","조안나":"최서연"}
{"date":"2023-02-20","day":"금","time":"19:30","스위니토드":"신성록","러빗부인":"김지현","터핀판사":"박인배","안소니":"노윤","토비아스":"윤석호","조안나":"류인아"}
{"date":"2023-02-21","day":"토","time":"14:00","스위니토드":"이규형","러빗부인":"린아","터핀판사":"김대종","안소니":"진태화","토비아스":"윤은오","조안나":"최서연"}
{"date":"2023-02-21","day":"토","time":"19:00","스위니토드":"강필석","러빗부인":"김지현","터핀판사":"김대종","안소니":"진태화","토비아스":"윤석오","조안나":"류인아"}
{"date":"2023-02-22","day":"일","time":"14:00","스위니토드":"신성록","러빗부인":"린아","터핀판사":"박인배","안소니":"노윤","토비아스":"윤은오","조안나":"최서연"}
{"date":"2023-02-22","day":"일","time":"19:00","스위니토드":"이규형","러빗부인":"전미도","터핀판사":"박인배","안소니":"노윤","토비아스":"윤석오","조안나":"류인아"}
{"date":"2023-02-23","day":"화","time":"19:30","스위니토드":"이규형","러빗부인":"린아","터핀판사":"김대종","안소니":"노윤","토비아스":"윤석오","조안나":"최서연"}
{"date":"2023-02-24","day":"수","time":"19:30","스위니토드":"신성록","러빗부인":"전미도","터핀판사":"박인배","안소니":"진태화","토비아스":"윤은오","조안나":"류인아"}
{"date":"2023-02-25","day":"목","time":"19:30","스위니토드":"강필석","러빗부인":"전미도","터핀판사":"김대종","안소니":"진태화","토비아스":"윤은오","조안나":"최서연"}
{"date":"2023-02-25","day":"금","time":"19:30","스위니토드":"신성록","러빗부인":"김지현","터핀판사":"박인배","안소니":"노윤","토비아스":"윤석호","조안나":"류인아"}
{"date":"2023-02-26","day":"토","time":"14:00","스위니토드":"이규형","러빗부인":"린아","터핀판사":"김대종","안소니":"진태화","토비아스":"윤은오","조안나":"최서연"}
{"date":"2023-02-26","day":"토","time":"19:00","스위니토드":"강필석","러빗부인":"김지현","터핀판사":"김대종","안소니":"진태화","토비아스":"윤석오","조안나":"류인아"}
{"date":"2023-02-27","day":"일","time":"14:00","스위니토드":"신성록","러빗부인":"린아","터핀판사":"박인배","안소니":"노윤","토비아스":"윤은오","조안나":"최서연"}
{"date":"2023-02-27","day":"일","time":"19:00","스위니토드":"이규형","러빗부인":"전미도","터핀판사":"박인배","안소니":"노윤","토비아스":"윤석오","조안나":"류인아"}
{"date":"2023-02-28","day":"화","time":"19:30","스위니토드":"이규형","러빗부인":"린아","터핀판사":"김대종","안소니":"노윤","토비아스":"윤석오","조안나":"최서연"}
{"date":"2023-03-01","day":"수","time":"19:30","스위니토드":"신성록","러빗부인":"전미도","터핀판사":"박인배","안소니":"진태화","토비아스":"윤은오","조안나":"류인아"}
{"date":"2023-03-02","day":"목","time":"19:30","스위니토드":"강필석","러빗부인":"전미도","터핀판사":"김대종","안소니":"진태화","토비아스":"윤은오","조안나":"최서연"}
{"date":"2023-03-03","day":"금","time":"19:30","스위니토드":"신성록","러빗부인":"김지현","터핀판사":"박인배","안소니":"노윤","토비아스":"윤석호","조안나":"류인아"}
{"date":"2023-03-04","day":"토","time":"14:00","스위니토드":"이규형","러빗부인":"린아","터핀판사":"김대종","안소니":"진태화","토비아스":"윤은오","조안나":"최서연"}
{"date":"2023-03-04","day":"토","time":"19:00","스위니토드":"강필석","러빗부인":"김지현","터핀판사":"김대종","안소니":"진태화","토비아스":"윤석오","조안나":"류인아"}
{"date":"2023-03-05","day":"일","time":"14:00","스위니토드":"신성록","러빗부인":"린아","터핀판사":"박인배","안소니":"노윤","토비아스":"윤은오","조안나":"최서연"}
{"date":"2023-03-05","day":"일","time":"19:00","스위니토드":"이규형","러빗부인":"전미도","터핀판사":"박인배","안소니":"노윤","토비아스":"윤석오","조안나":"류인아"}